crypto_commons/__init__.py
crypto_commons/types/__init__.py
crypto_commons/types/quote.py
crypto_commons/types/token_info.py
crypto_commons/types/token_state.py
byteforge_crypto_commons-0.2.dist-info/METADATA
byteforge_crypto_commons-0.2.dist-info/WHEEL
byteforge_crypto_commons-0.2.dist-info/licenses/LICENSE
byteforge_crypto_commons-0.2.dist-info/RECORD
