Metadata-Version: 2.4
Name: byteforge-crypto-commons
Version: 0.2
Summary: Common models and dependencies for crypto projects.
Project-URL: Homepage, https://github.com/jmazzahacks/byteforge-crypto-commons
Project-URL: Issues, https://github.com/jmazzahacks/byteforge-crypto-commons/issues
Author: Jason Byteforge
License:                              Apache License
License-File: LICENSE
Keywords: API,byteforge,byteforge-coinmarketcap,cryptocurrency,crytpo
Classifier: License :: OSI Approved :: MIT License
Classifier: Operating System :: OS Independent
Classifier: Programming Language :: Python :: 3
Requires-Python: >=3.8
Requires-Dist: python-dateutil
